pyawait/__init__.py
pyawait/__main__.py
pyawait/await-aarch64
pyawait/await-armv7l
pyawait/await-x86_64
pyawait-0.1.6.dist-info/LICENSE
pyawait-0.1.6.dist-info/METADATA
pyawait-0.1.6.dist-info/WHEEL
pyawait-0.1.6.dist-info/entry_points.txt
pyawait-0.1.6.dist-info/top_level.txt
pyawait-0.1.6.dist-info/RECORD
