Metadata-Version: 2.1
Name: pyawait
Version: 0.1.6
Summary: Wait until TCP endpoints are open
Author-email: Andrii Kuzmin <jack.cvr@gmail.com>
Project-URL: Documentation, https://github.com/jackcvr/await#readme
Project-URL: Issues, https://github.com/jackcvr/await/issues
Project-URL: Source, https://github.com/jackcvr/await
Keywords: wait-for-it,waitforit,await,tcp,docker
Classifier: Programming Language :: Python
Classifier: Programming Language :: Python :: 3
Requires-Python: >=3
License-File: LICENSE
